pingpongsdk/__init__.py
pingpongsdk/deployments/__init__.py
pingpongsdk/deployments/deployments.py
pingpongsdk/deployments/model.py
pingpongsdk/deployments/test_deployments.py
pingpongsdk/models/__init__.py
pingpongsdk/models/model.py
pingpongsdk/models/models.py
pingpongsdk/models/test_models.py
pingpongsdk/shared/__init__.py
pingpongsdk/shared/client/__init__.py
pingpongsdk/shared/client/client.py
pingpongsdk/tests/__init__.py
pingpongsdk-0.1.5.dist-info/METADATA
pingpongsdk-0.1.5.dist-info/WHEEL
pingpongsdk-0.1.5.dist-info/RECORD
