Metadata-Version: 2.1
Name: pingpongsdk
Version: 0.1.5
Summary: 
Author: Ewan Valentine
Author-email: ewan.valentine89@gmail.com
Requires-Python: >=3.7,<4.0
Classifier: Programming Language :: Python :: 3
Classifier: Programming Language :: Python :: 3.7
Classifier: Programming Language :: Python :: 3.8
Classifier: Programming Language :: Python :: 3.9
Classifier: Programming Language :: Python :: 3.10
Classifier: Programming Language :: Python :: 3.11
